sat_vis/__init__.py
sat_vis/int_tree_converter.py
sat_vis/schedule_plots.py
sat_vis/vis_history.py
sat_vis/visibility_func.py
sat_vis-0.0.3.dist-info/LICENSE
sat_vis-0.0.3.dist-info/METADATA
sat_vis-0.0.3.dist-info/WHEEL
sat_vis-0.0.3.dist-info/top_level.txt
sat_vis-0.0.3.dist-info/RECORD
