Metadata-Version: 2.1
Name: sat-vis
Version: 0.0.3
Summary: Satellite LOS visibility calculator
Author-email: Dylan Penn <dylanrpenn@vt.edu>
License: MIT License
Project-URL: Homepage, https://github.com/dylan906/sat-vis
Classifier: Programming Language :: Python :: 3
Classifier: License :: OSI Approved :: MIT License
Classifier: Operating System :: OS Independent
Requires-Python: >=3
License-File: LICENSE
Requires-Dist: matplotlib (>=3.5)
Requires-Dist: intervaltree (>=3.1)
Requires-Dist: numpy (>=1.23)
Provides-Extra: dev
Requires-Dist: flake8 ; extra == 'dev'
Requires-Dist: pylint ; extra == 'dev'
Requires-Dist: pytest ; extra == 'dev'
Requires-Dist: flake8-bugbear (==22.4.25) ; extra == 'dev'
Requires-Dist: flake8-builtins (==1.5.3) ; extra == 'dev'
Requires-Dist: flake8-docstrings (==1.6.0) ; extra == 'dev'
Requires-Dist: flake8-plugin-utils (==1.3.2) ; extra == 'dev'
Requires-Dist: flake8-pytest-style (==1.6.0) ; extra == 'dev'
Requires-Dist: flake8-rst-docstrings (==0.2.6) ; extra == 'dev'
Requires-Dist: black (>=22.3.0) ; extra == 'dev'
Requires-Dist: isort[colors] ; extra == 'dev'
